foocat_pzy/__init__.py
foocat_pzy/foocat_pzy.py
foocat_pzy-0.1.0.dist-info/LICENSE
foocat_pzy-0.1.0.dist-info/WHEEL
foocat_pzy-0.1.0.dist-info/METADATA
foocat_pzy-0.1.0.dist-info/RECORD
